_MQLib.cpython-37m-x86_64-linux-gnu.so
MQLib/__init__.py
MQLib/hhdata/MERZ2002KOPT.rf
MQLib/hhdata/BEASLEY1998TS.rf
MQLib/hhdata/FESTA2002GVNS.rf
MQLib/hhdata/MERZ2004.rf
MQLib/hhdata/MERZ1999GLS.rf
MQLib/hhdata/HASAN2000GA.rf
MQLib/hhdata/PALUBECKIS2004bMST5.rf
MQLib/hhdata/PALUBECKIS2006.rf
MQLib/hhdata/DUARTE2005.rf
MQLib/hhdata/MERZ1999MUTATE.rf
MQLib/hhdata/KATAYAMA2001.rf
MQLib/hhdata/PALUBECKIS2004bSTS.rf
MQLib/hhdata/PALUBECKIS2004bMST4.rf
MQLib/hhdata/GLOVER2010.rf
MQLib/hhdata/FESTA2002GPR.rf
MQLib/hhdata/FESTA2002VNSPR.rf
MQLib/hhdata/MERZ1999CROSS.rf
MQLib/hhdata/PALUBECKIS2004bMST3.rf
MQLib/hhdata/GLOVER1998a.rf
MQLib/hhdata/BURER2002.rf
MQLib/hhdata/PARDALOS2008.rf
MQLib/hhdata/MERZ2002GREEDYKOPT.rf
MQLib/hhdata/LAGUNA2009HCE.rf
MQLib/hhdata/KATAYAMA2000.rf
MQLib/hhdata/PALUBECKIS2004bMST1.rf
MQLib/hhdata/FESTA2002G.rf
MQLib/hhdata/MERZ2002GREEDY.rf
MQLib/hhdata/BEASLEY1998SA.rf
MQLib/hhdata/LU2010.rf
MQLib/hhdata/PALUBECKIS2004bMST2.rf
MQLib/hhdata/ALKHAMIS1998.rf
MQLib/hhdata/LODI1999.rf
MQLib/hhdata/FESTA2002VNS.rf
MQLib/hhdata/HASAN2000TS.rf
MQLib/hhdata/FESTA2002GVNSPR.rf
MQLib/hhdata/MERZ2002ONEOPT.rf
MQLib-0.1.dist-info/top_level.txt
MQLib-0.1.dist-info/RECORD
MQLib-0.1.dist-info/LICENSE
MQLib-0.1.dist-info/WHEEL
MQLib-0.1.dist-info/METADATA
