Metadata-Version: 2.1
Name: MQLib
Version: 0.1
Summary: Heuristics for the Max-cut and QUBO combinatorial optimization problems
Home-page: https://github.com/MQLib/MQLib
Author: Iain Dunning, Swati Gupta, and John Silberholz
Author-email: john.silberholz@gmail.com
License: UNKNOWN
Platform: UNKNOWN
Classifier: Development Status :: 3 - Alpha
Classifier: Intended Audience :: Developers
Classifier: Intended Audience :: Science/Research
Classifier: Programming Language :: Python :: 3
Classifier: Programming Language :: C++
Classifier: License :: OSI Approved :: MIT License
Classifier: Operating System :: OS Independent
Requires-Python: >=3.5
Requires-Dist: numpy
Requires-Dist: scipy
Requires-Dist: networkx
